pydantic_ai_optimizers/__init__.py
pydantic_ai_optimizers/agents/prompts/reflection_instructions.txt
pydantic_ai_optimizers/agents/reflection_agent.py
pydantic_ai_optimizers/cli.py
pydantic_ai_optimizers/config.py
pydantic_ai_optimizers/optimizer.py
pydantic_ai_optimizers-0.0.2.dist-info/WHEEL
pydantic_ai_optimizers-0.0.2.dist-info/entry_points.txt
pydantic_ai_optimizers-0.0.2.dist-info/METADATA
pydantic_ai_optimizers-0.0.2.dist-info/RECORD
