Metadata-Version: 2.3
Name: pydantic-ai-optimizers
Version: 0.0.2
Summary: A library for optimizing PydanticAI agents prompts through iterative improvement and evaluation, built on top of PydanticAI + Pydantic Evals.
Keywords: pydantic,ai,optimizers,llm
Author: Jan Siml
Author-email: Jan Siml <49557684+svilupp@users.noreply.github.com>
License: MIT
Classifier: Development Status :: 3 - Alpha
Classifier: Intended Audience :: Developers
Classifier: License :: OSI Approved :: MIT License
Classifier: Programming Language :: Python :: 3
Classifier: Programming Language :: Python :: 3.13
Requires-Dist: logfire>=4.3.3
Requires-Dist: loguru>=0.7.3
Requires-Dist: pydantic-ai>=0.7.2
Requires-Dist: pydantic-ai-helpers>=0.0.2
Requires-Dist: pydantic-evals>=0.7.2
Requires-Dist: python-dotenv>=1.1.1
Requires-Dist: textprompts>=0.0.4
Requires-Dist: pytest>=8.4.1 ; extra == 'dev'
Requires-Dist: pytest-cov>=6.2.1 ; extra == 'dev'
Requires-Dist: pytest-asyncio>=0.21.0 ; extra == 'dev'
Requires-Dist: ruff>=0.12.9 ; extra == 'dev'
Requires-Dist: mypy>=1.8.0 ; extra == 'dev'
Requires-Dist: pre-commit>=3.6.0 ; extra == 'dev'
Requires-Python: >=3.11
Project-URL: Homepage, https://github.com/svilupp/pydantic-ai-optimizers
Project-URL: Issues, https://github.com/svilupp/pydantic-ai-optimizers/issues
Project-URL: Repository, https://github.com/svilupp/pydantic-ai-optimizers
Provides-Extra: dev
